azure_recommendations_7/__init__.py
azure_recommendations_7/recommendation/__init__.py
azure_recommendations_7/recommendation/advisor_recommendations.py
azure_recommendations_7/recommendation/network_recommendations.py
azure_recommendations_7/recommendation/utils.py
azure_recommendations_7/recommendation/vm_recommendations.py
azure_recommendations_7-0.1.6.dist-info/LICENCE
azure_recommendations_7-0.1.6.dist-info/METADATA
azure_recommendations_7-0.1.6.dist-info/WHEEL
azure_recommendations_7-0.1.6.dist-info/top_level.txt
azure_recommendations_7-0.1.6.dist-info/RECORD
