Metadata-Version: 2.1
Name: azure-recommendations-7
Version: 0.1.6
Summary: Provides Azure recommendations
Author-email: "dheeraj.banodha" <dheeraj.banodha@impetus.com>
Classifier: Programming Language :: Python :: 3
Classifier: Operating System :: OS Independent
Requires-Python: >=3.7
License-File: LICENCE
